make_distribution/__init__.py
make_distribution/client.py
make_distribution/distributions.py
make_distribution-0.2.0.dist-info/LICENSE
make_distribution-0.2.0.dist-info/METADATA
make_distribution-0.2.0.dist-info/WHEEL
make_distribution-0.2.0.dist-info/RECORD
