Metadata-Version: 2.1
Name: make_distribution
Version: 0.2.0
Summary: Top-level package for MakeDistribution.com Python client.
Home-page: https://github.com/tadamcz/make_distribution_python_client
License: MIT
Author: Tom Adamczewski
Author-email: tadamczewskipublic@gmail.com
Requires-Python: >=3.9,<4
Classifier: License :: OSI Approved :: MIT License
Classifier: Natural Language :: English
Classifier: Programming Language :: Python :: 3
Classifier: Programming Language :: Python :: 3.9
Classifier: Programming Language :: Python :: 3.10
Classifier: Programming Language :: Python :: 3.11
Classifier: Programming Language :: Python :: 3.12
Requires-Dist: numpy (>=1.26.4,<2.0.0)
Requires-Dist: requests (>=2.31.0,<3.0.0)
